README.md
setup.cfg
setup.py
transmission.py
transmission_putio.egg-info/PKG-INFO
transmission_putio.egg-info/SOURCES.txt
transmission_putio.egg-info/dependency_links.txt
transmission_putio.egg-info/requires.txt
transmission_putio.egg-info/top_level.txt
transmission_putio.egg-info/zip-safe