Metadata-Version: 1.1
Name: transmission-putio
Version: 1.0.3
Summary: Client for Transmission RPC Server
Home-page: https://github.com/putdotio/python-transmission-rpc
Author: Cenk Altı
Author-email: cenkalti@gmail.com
License: UNKNOWN
Platform: any
Classifier: Programming Language :: Python :: 3
